streamlit_fesion/__init__.py
streamlit_fesion/_version.py
streamlit_fesion/image_filter.py
streamlit_fesion/frontend/dist/index.html
streamlit_fesion/frontend/dist/assets/index-AlYqImA5.js
streamlit_fesion-0.5.6.dist-info/METADATA
streamlit_fesion-0.5.6.dist-info/WHEEL
streamlit_fesion-0.5.6.dist-info/licenses/LICENSE
streamlit_fesion-0.5.6.dist-info/RECORD
