Metadata-Version: 2.4
Name: streamlit-fesion
Version: 0.5.6
Project-URL: Repository, https://github.com/whitphx/streamlit-webrtc
Author-email: "Yuichiro Tachibana (Tsuchiya)" <t.yic.yt@gmail.com>
License-Expression: MIT
License-File: LICENSE
Requires-Python: !=3.9.7,>=3.9
Requires-Dist: streamlit>=1.0.0
